qjtestmcp01/__init__.py
qjtestmcp01-0.1.0.dist-info/WHEEL
qjtestmcp01-0.1.0.dist-info/entry_points.txt
qjtestmcp01-0.1.0.dist-info/METADATA
qjtestmcp01-0.1.0.dist-info/RECORD
