Metadata-Version: 2.3
Name: qjtestmcp01
Version: 0.1.0
Summary: Add your description here
Author: qiao jian
Author-email: qiao jian <qj189@qq.com>
Requires-Dist: mcp[cli]>=1.12.4
Requires-Python: >=3.13
